politicsnlp/__init__.py
politicsnlp/authoritarianism.py
politicsnlp/centralization.py
politicsnlp/civil_war.py
politicsnlp/dark_money.py
politicsnlp/de_orientalizing.py
politicsnlp/dictatorship.py
politicsnlp/ethnic_regional_autonomy.py
politicsnlp/false_flag_operation.py
politicsnlp/government.py
politicsnlp/hate_speech.py
politicsnlp/information_literacy.py
politicsnlp/intelligence.py
politicsnlp/limited_power.py
politicsnlp/military_coup.py
politicsnlp/national_interest.py
politicsnlp/protection.py
politicsnlp/purges.py
politicsnlp/revolution.py
politicsnlp/rhetoric.py
politicsnlp/sanctions.py
politicsnlp/social_contract.py
politicsnlp/tense_air.py
politicsnlp/territory.py
politicsnlp/the_tyranny_of_the_majority.py
politicsnlp/diplomacy/__init__.py
politicsnlp/diplomacy/coercive_diplomacy.py
politicsnlp/diplomacy/hegemony.py
politicsnlp/diplomacy/wolf_warrior_diplomacy.py
politicsnlp/form_of_government/__init__.py
politicsnlp/form_of_government/aristocracy.py
politicsnlp/form_of_government/autocracy.py
politicsnlp/form_of_government/colonialism.py
politicsnlp/form_of_government/communism.py
politicsnlp/form_of_government/direct_democracy.py
politicsnlp/form_of_government/monarchy.py
politicsnlp/form_of_government/oligarchy.py
politicsnlp/form_of_government/regime.py
politicsnlp/form_of_government/representative_democracy.py
politicsnlp/form_of_government/socialism.py
politicsnlp/form_of_government/theocracy.py
politicsnlp/ideology/__init__.py
politicsnlp/ideology/confucianism.py
politicsnlp/ideology/economic_liberalism.py
politicsnlp/ideology/green_politics.py
politicsnlp/ideology/ideology.py
politicsnlp/ideology/liberalism.py
politicsnlp/ideology/nationalism.py
politicsnlp/ideology/ordoliberalism.py
politicsnlp/ideology/populism.py
politicsnlp/ideology/social_liberalism.py
politicsnlp/individual/__init__.py
politicsnlp/individual/civil_servant.py
politicsnlp/individual/individual.py
politicsnlp/individual/monarch.py
politicsnlp/individual/strongman.py
politicsnlp-0.0.21.dist-info/LICENSE
politicsnlp-0.0.21.dist-info/METADATA
politicsnlp-0.0.21.dist-info/WHEEL
politicsnlp-0.0.21.dist-info/top_level.txt
politicsnlp-0.0.21.dist-info/RECORD
