Metadata-Version: 2.1
Name: politicsnlp
Version: 0.0.21
Summary: Python Narrating Politics
Home-page: https://cpanlp.com
Author: Draco Deng
Author-email: dracodeng6@gmail.com
License: MIT
Keywords: python,politics,freedom,justice,power,democracy,party,intelligent politics,linguistic turn,linguistic,intelligent party,natural language processing,machine learning,policy
Classifier: Intended Audience :: Developers
Classifier: License :: OSI Approved :: MIT License
Classifier: Programming Language :: Python :: 3
Classifier: Operating System :: Unix
Classifier: Operating System :: MacOS :: MacOS X
Classifier: Operating System :: Microsoft :: Windows
Classifier: Natural Language :: English
License-File: LICENSE
